[
  {
    "id": 493948438,
    "image": "benefitsVitaminD.svg",
    "dateDay": 25,
    "dateMonth": "Nov",
    "authour": "Rachi Card",
    "title": "The Benefits of Vitamin D & How to Get It",
    "text": "Simply dummy text of the printing and typesetting industry. Lorem Ipsum"
  },
  {
    "id": 493163438,
    "image": "summertimeTomato.svg",
    "dateDay": 25,
    "dateMonth": "Nov",
    "authour": "Rachi Card",
    "title": "Our Favourite Summertime Tomato",
    "text": "Simply dummy text of the printing and typesetting industry. Lorem Ipsum"
  },
  {
    "id": 843948438,
    "image": "benefitsVitaminC.svg",
    "dateDay": 25,
    "dateMonth": "Nov",
    "authour": "Rachi Card",
    "title": "Benefits of Vitamin C & How to Get It",
    "text": "Simply dummy text of the printing and typesetting industry. Lorem Ipsum"
  },
  {
    "id": 493949128,
    "image": "reserch.svg",
    "dateDay": 25,
    "dateMonth": "Nov",
    "authour": "Rachi Card",
    "title": "Research More Organic Foods",
    "text": "Simply dummy text of the printing and typesetting industry. Lorem Ipsum"
  },
  {
    "id": 713948438,
    "image": "freshFruits.svg",
    "dateDay": 25,
    "dateMonth": "Nov",
    "authour": "Rachi Card",
    "title": "Everyday Fresh Fruites",
    "text": "Simply dummy text of the printing and typesetting industry. Lorem Ipsum"
  },
  {
    "id": 303948438,
    "image": "dontUsePlastic.svg",
    "dateDay": 25,
    "dateMonth": "Nov",
    "authour": "Rachi Card",
    "title": "Don’t Use Plastic Product! it’s Kill Nature",
    "text": "Simply dummy text of the printing and typesetting industry. Lorem Ipsum"
  }
]


